MANIFEST.in
README.md
requirements.txt
setup.md
setup.py
py_femas/__init__.py
py_femas/ctp_enum.py
py_femas/ctp_quote.py
py_femas/ctp_struct.py
py_femas/ctp_trade.py
py_femas/enums.py
py_femas/quote.py
py_femas/structs.py
py_femas/test_api.py
py_femas/trade.py
py_femas.egg-info/PKG-INFO
py_femas.egg-info/SOURCES.txt
py_femas.egg-info/dependency_links.txt
py_femas.egg-info/top_level.txt
py_femas/lib32/USTPmduserapiAF.dll
py_femas/lib32/USTPtraderapiAF.dll
py_femas/lib32/ctp_quote.dll
py_femas/lib32/ctp_trade.dll
py_femas/lib64/USTPmduserapiAF.dll
py_femas/lib64/USTPtraderapiAF.dll
py_femas/lib64/ctp_quote.dll
py_femas/lib64/ctp_quote.so
py_femas/lib64/ctp_trade.dll
py_femas/lib64/ctp_trade.so
py_femas/lib64/libUSTPmduserapiAF.so
py_femas/lib64/libUSTPtraderapiAF.so