Metadata-Version: 2.1
Name: py-femas
Version: 0.0.3
Summary: Python Femas futures api
Home-page: https://github.com/haifengat/hf_femas
Author: HaiFeng
Author-email: haifengat@vip.qq.com
License: MIT License
Platform: any
Classifier: Programming Language :: Python :: 3.7
Classifier: License :: OSI Approved :: MIT License
Classifier: Operating System :: OS Independent
Requires-Python: >=3.7.0
